discord_bot_helper/__init__.py
discord_bot_helper/__main__.py
discord_bot_helper/bot_setup.py
discord_bot_helper/config_setup.py
discord_bot_helper-1.0.0.dist-info/licenses/LICENSE
discord_bot_helper-1.0.0.dist-info/METADATA
discord_bot_helper-1.0.0.dist-info/WHEEL
discord_bot_helper-1.0.0.dist-info/entry_points.txt
discord_bot_helper-1.0.0.dist-info/top_level.txt
discord_bot_helper-1.0.0.dist-info/RECORD
