Metadata-Version: 2.4
Name: discord-bot-helper
Version: 1.0.0
Summary: Discord Bot Setup Assistant
Home-page: https://github.com/KeiraOMG0/discord-bot-helper
Author: Keira
Classifier: Programming Language :: Python :: 3
Classifier: License :: OSI Approved :: MIT License
Classifier: Operating System :: OS Independent
Requires-Python: >=3.9
License-File: LICENSE
Requires-Dist: discord.py>=2.3.0
Requires-Dist: python-dotenv>=1.0.0
Dynamic: author
Dynamic: classifier
Dynamic: description
Dynamic: description-content-type
Dynamic: home-page
Dynamic: license-file
Dynamic: requires-dist
Dynamic: requires-python
Dynamic: summary
